vsgmfss_union/FusionNet.py
vsgmfss_union/IFNet_HDv3.py
vsgmfss_union/MetricNet.py
vsgmfss_union/__init__.py
vsgmfss_union/gmfss.py
vsgmfss_union/softsplat.py
vsgmfss_union/util.py
vsgmfss_union/warplayer.py
vsgmfss_union/gmflow/__init__.py
vsgmfss_union/gmflow/backbone.py
vsgmfss_union/gmflow/geometry.py
vsgmfss_union/gmflow/gmflow.py
vsgmfss_union/gmflow/matching.py
vsgmfss_union/gmflow/position.py
vsgmfss_union/gmflow/transformer.py
vsgmfss_union/gmflow/trident_conv.py
vsgmfss_union/gmflow/utils.py
vsgmfss_union/models/flownet.pkl
vsgmfss_union/models/fusionnet_vanillagan.pkl
vsgmfss_union/models/fusionnet_wgan.pkl
vsgmfss_union/models/metric_vanillagan.pkl
vsgmfss_union/models/metric_wgan.pkl
vsgmfss_union/models/rife.pkl
vsgmfss_union-1.1.0.dist-info/METADATA
vsgmfss_union-1.1.0.dist-info/WHEEL
vsgmfss_union-1.1.0.dist-info/licenses/LICENSE
vsgmfss_union-1.1.0.dist-info/RECORD
