Metadata-Version: 2.1
Name: vsgmfss_union
Version: 1.1.0
Summary: GMFSS_union function for VapourSynth
Project-URL: Homepage, https://github.com/HolyWu/vs-gmfss_union
Project-URL: Bug Tracker, https://github.com/HolyWu/vs-gmfss_union/issues
Author-email: HolyWu <holywu@gmail.com>
License: MIT License
License-File: LICENSE
Keywords: GMFSS_union,VapourSynth
Classifier: License :: OSI Approved :: MIT License
Classifier: Operating System :: OS Independent
Classifier: Programming Language :: Python :: 3.10
Classifier: Topic :: Multimedia :: Video
Requires-Python: >=3.10
Requires-Dist: cupy-cuda11x
Requires-Dist: numpy
Requires-Dist: tensorrt>=8.5.2.2
Requires-Dist: torch-tensorrt-fx-only>=1.3.0
Requires-Dist: torch>=1.13.0
Requires-Dist: vapoursynth>=55
